{
  "section_id": "EC-669",
  "code": "EVID",
  "section": "669.1",
  "title": "Public Entity Rule or Policy Not Statute Presumption Limitation",
  "text": "A rule, policy, manual, or guideline of state or local government setting forth standards of conduct or guidelines for its employees in the conduct of their public employment shall not be considered a statute, ordinance, or regulation of that public entity within the meaning of Section 669, unless the rule, manual, policy, or guideline has been formally adopted as a statute, as an ordinance of a local governmental entity in this state empowered to adopt ordinances, or as a regulation by an agency of the state pursuant to the Administrative Procedure Act (Chapter 3.5 (commencing with Section 11340) of Division 3 of Title 2 of the Government Code), or by an agency of the United States government pursuant to the federal Administrative Procedure Act (Chapter 5 (commencing with Section 5001) of Title 5 of the United States Code). This section affects only the presumption set forth in Section 669, and is not otherwise intended to affect the admissibility or inadmissibility of the rule, policy, manual, or guideline under other provisions of law.",
  "notes": null,
  "rule_type": "presumption",
  "rule_type_confidence": "heuristic",
  "applies_to": [],
  "evidentiary_standard": null,
  "foundation_requirements": [],
  "cross_refs": [],
  "coa_relevance": [],
  "exclusion_grounds": [],
  "tags": [
    "presumption",
    "public_entity",
    "rule",
    "policy",
    "manual",
    "guideline"
  ],
  "structure": {
    "division": "5",
    "division_title": "Burden of Proof; Burden of Producing Evidence; Presumptions and Inferences",
    "chapter": null,
    "chapter_title": null,
    "article": null,
    "article_title": null
  },
  "canonical_type": "source",
  "source": {
    "type": "ca_legislature",
    "jurisdiction": "California",
    "url": "https://leginfo.legislature.ca.gov",
    "editorial_note": null
  },
  "effective_date": null,
  "schema_version": "1.0",
  "pass1_complete": true,
  "pass2_complete": false,
  "source_file": "EVID_669_1.json"
}