{
  "code": "EVID",
  "section": "1323",
  "title": "Statement Concerning Land Boundary",
  "text": "Evidence of a statement concerning the boundary of land is not made inadmissible by the hearsay rule if the declarant is unavailable as a witness and had sufficient knowledge of the subject, but evidence of a statement is not admissible under this section if the statement was made under circumstances such as to indicate its lack of trustworthiness.",
  "tags": [
    "hearsay",
    "exception",
    "land_boundary",
    "declarant_unavailable"
  ],
  "structure": {
    "division": "10",
    "division_title": "Hearsay Evidence",
    "chapter": "2",
    "chapter_title": "Hearsay Exceptions",
    "article": "12",
    "article_title": "Reputation and Statements Concerning Community History, Property Interests, and Character"
  },
  "source": {
    "type": "ca_legislature",
    "jurisdiction": "California",
    "url": "https://leginfo.legislature.ca.gov",
    "editorial_note": "Enacted by Stats. 1965, Ch. 299."
  }
}
