{
  "code": "CACI",
  "instruction_id": "2509",
  "title": "\u201cAdverse Employment Action\u201d Explained",
  "series": "2500",
  "series_title": "Fair Employment and Housing Act (FEHA)",
  "text": "[Name of plaintiff ] must prove that [he/she/ nonbinary pronoun] was\nsubjected to an adverse employment action.\nAdverse employment actions are not limited to ultimate actions such as\ntermination or demotion. There is an adverse employment action if\n[name of defendant ] has taken an action or engaged in a course or\npattern of conduct that, taken as a whole, materially and adversely\naffected the terms, conditions, or privileges of [ name of plaintiff ]\u2019s\nemployment. An adverse employment action includes conduct that is\nreasonably likely to impair a reasonable employee\u2019s job performance or\nprospects for advancement or promotion. However, minor or trivial\nactions or conduct that is not reasonably likely to do more than anger or\nupset an employee cannot constitute an adverse employment action.\nNew June 2012",
  "tags": [
    "discrimination",
    "feha"
  ],
  "source": {
    "type": "caci_judicial_council",
    "jurisdiction": "California",
    "edition": "2026",
    "url": "https://www.courts.ca.gov/partners/317.htm",
    "editorial_note": "Parsed from CACI 2026 edition PDF"
  },
  "directions_for_use": "Give this instruction with CACI No. 2500, Disparate Treatment\u2014Essential Factual\nElements, CACI No. 2505, Retaliation, CACI No. 2540, Disability\nDiscrimination\u2014Disparate Treatment\u2014Essential Factual Elements , CACI No. 2560,\nReligious Creed Discrimination\u2014Failure to Accommodate\u2014Essential Factual\nElements, or CACI No. 2570, Age Discrimination\u2014Disparate Treatment\u2014Essential\nFactual Elements, if there is an issue as to whether the employee was the victim of\nan adverse employment action.\nFor example, the case may involve a pattern of employer harassment consisting of\nacts that might not individually be sufficient to constitute discrimination or\nretaliation, but taken as a whole establish prohibited conduct. (See Yanowitz v.\nL\u2019Oreal USA, Inc. (2005) 36 Cal.4th 1028, 1052\u20131056 [32 Cal.Rptr.3d 436, 116\nP .3d 1123].) Or the case may involve acts that, considered alone, would not appear\nto be adverse, but could be adverse under the particular circumstances of the case.\n(See Patten v. Grant Joint Union High School Dist. (2005) 134 Cal.App.4th 1378,\n1389\u20131390 [37 Cal.Rptr.3d 113] [lateral transfer can be adverse employment action\neven if wages, bene\ufb01ts, and duties remain the same].)",
  "sources_and_authority": "\u2022 \u201cAppropriately viewed, [section 12940(a)] protects an employee against unlawful\ndiscrimination with respect not only to so-called ultimate employment actions\nsuch as termination or demotion, but also the entire spectrum of employment\nactions that are reasonably likely to adversely and materially affect an\nemployee\u2019s job performance or opportunity for advancement in his or her career.\nAlthough a mere offensive utterance or even a pattern of social slights by either\nthe employer or coemployees cannot properly be viewed as materially affecting\n1566\n\nthe terms, conditions, or privileges of employment for purposes of section\n12940(a) (or give rise to a claim under section 12940(h)), the phrase \u2018terms,\nconditions, or privileges\u2019 of employment must be interpreted liberally and with a\nreasonable appreciation of the realities of the workplace in order to afford\nemployees the appropriate and generous protection against employment\ndiscrimination that the FEHA was intended to provide.\u201d ( Yanowitz, supra, 36\nCal.4th at pp. 1053\u20131054, footnotes omitted.)\n\u2022 \u201c[T]he determination of what type of adverse treatment properly should be\nconsidered discrimination in the terms, conditions, or privileges of employment\nis not, by its nature, susceptible to a mathematically precise test, and the\nsigni\ufb01cance of particular types of adverse actions must be evaluated by taking\ninto account the legitimate interests of both the employer and the employee.\nMinor or relatively trivial adverse actions or conduct by employers or fellow\nemployees that, from an objective perspective, are reasonably likely to do no\nmore than anger or upset an employee cannot properly be viewed as materially\naffecting the terms, conditions, or privileges of employment and are not\nactionable, but adverse treatment that is reasonably likely to impair a reasonable\nemployee\u2019s job performance or prospects for advancement or promotion falls\nwithin the reach of the antidiscrimination provisions of sections 12940(a) and\n12940(h).\u201d ( Yanowitz, supra, 36 Cal.4th at pp. 1054\u20131055.)\n\u2022 \u201cAn \u2018 \u201cadverse employment action,\u201d \u2019 . . . , requires a \u2018substantial adverse\nchange in the terms and conditions of the plaintiff\u2019s employment\u2019. \u201d ( Holmes v.\nPetrovich Development Co., LLC (2011) 191 Cal.App.4th 1047, 1063 [119\nCal.Rptr.3d 878, internal citations omitted.)\n\u2022 \u201cContrary to [defendant]\u2019s assertion that it is improper to consider collectively\nthe alleged retaliatory acts, there is no requirement that an employer\u2019s retaliatory\nacts constitute one swift blow, rather than a series of subtle, yet damaging,\ninjuries. Enforcing a requirement that each act separately constitute an adverse\nemployment action would subvert the purpose and intent of the statute.\u201d\n(Yanowitz, supra, 36 Cal.4th at pp. 1055\u20131056, internal citations omitted.)\n\u2022 \u201cMoreover, [defendant]\u2019s actions had a substantial and material impact on the\nconditions of employment. The refusal to promote [plaintiff] is an adverse\nemployment action under FEHA. There was also a pattern of conduct, the\ntotality of which constitutes an adverse employment action. This includes\nundeserved negative job reviews, reductions in his staff, ignoring his health\nconcerns and acts which caused him substantial psychological harm.\u201d ( Wysinger\nv. Automobile Club of Southern California (2007) 157 Cal.App.4th 413, 424 [69\nCal.Rptr.3d 1], internal citations omitted.)\n\u2022 \u201cThe employment action must be both detrimental and substantial . . . [\u00b6]. We\nmust analyze [plaintiff\u2019s] complaints of adverse employment actions to determine\nif they result in a material change in the terms of her employment, impair her\nemployment in some cognizable manner, or show some other employment injury\n. . . . [W]e do not \ufb01nd that [plaintiff\u2019s] complaint alleges the necessary material\nchanges in the terms of her employment to cause employment injury. Most of"
}