{
  "code": "CACI",
  "instruction_id": "2522B",
  "title": "Work Environment Harassment\u2014Conduct Directed at Others\u2014Essential Factual",
  "series": "2500",
  "series_title": "Fair Employment and Housing Act (FEHA)",
  "text": "Elements\u2014Individual Defendant (Gov. Code, \u00a7\u00a7 12923, 12940(j))\n2522C. Work Environment Harassment\u2014Sexual Favoritism\u2014Essential Factual\nElements\u2014Individual Defendant (Gov. Code, \u00a7\u00a7 12923, 12940(j))\n2523. \u201cHarassing Conduct\u201d Explained",
  "tags": [
    "discrimination",
    "feha",
    "harassment"
  ],
  "source": {
    "type": "caci_judicial_council",
    "jurisdiction": "California",
    "edition": "2026",
    "url": "https://www.courts.ca.gov/partners/317.htm",
    "editorial_note": "Parsed from CACI 2026 edition PDF"
  }
}