{
  "code": "CACI",
  "instruction_id": "3500",
  "title": "Introductory Instruction",
  "series": "3500",
  "series_title": "Construction Law",
  "text": "Public agencies such as the [ name of condemnor ] have the right to take\nprivate property for public use if they pay the owner just compensation.\nNew September 2003",
  "tags": [],
  "source": {
    "type": "caci_judicial_council",
    "jurisdiction": "California",
    "edition": "2026",
    "url": "https://www.courts.ca.gov/partners/317.htm",
    "editorial_note": "Parsed from CACI 2026 edition PDF"
  },
  "sources_and_authority": "\u2022 Constitutional Right of Eminent Domain. Article I, section 19, of the California\nConstitution.\n\u2022 Just Compensation. The Fifth Amendment of the U.S. Constitution.\n\u2022 Acquisition of Property for Public Use. Code of Civil Procedure section\n1240.010.\n\u2022 \u201cThe power of eminent domain arises as an inherent attribute of sovereignty that\nis necessary for government to exist. Properly exercised, the eminent domain\npower effects a compromise between the public good for which private land is\ntaken, and the protection and indemni\ufb01cation of private citizens whose property\nis taken to advance that public good. The Fifth Amendment of the United States\nConstitution, made applicable to the states by the Fourteenth Amendment, and\nCalifornia Constitution, article I, section 19 require this protection of private\ncitizens\u2019 property.\u201d ( Burbank-Glendale-Pasadena Airport Authority v. Hensler\n(2000) 83 Cal.App.4th 556, 561 [99 Cal.Rptr.2d 729], internal citation omitted.)\n\u2022 \u201cOur Constitution thus guarantees landowners the right to have a jury determine\nthe amount of just compensation owed for a taking.\u201d ( City of Perris v. Stamper\n(2016) 1 Cal.5th 576, 593 [205 Cal.Rptr.3d 797, 376 P .3d 1221].)\n\u2022 \u201cThis \u2018just compensation\u2019 clause in the California Constitution applies to the\nstate\u2019s exercise of its eminent domain power, constraining it by requiring that\nwhen the state takes private property for public use, the private property owner\nis justly compensated.\u201d ( City of Oroville v. Superior Court (2019) 7 Cal.5th\n1091, 1102 [250 Cal.Rptr.3d 803, 446 P .3d 304].)\n\u2022 \u201c \u2018An inverse condemnation action is an eminent domain proceeding initiated by\nthe property owner rather than the condemner. The principles which affect the\nparties\u2019 rights in an inverse condemnation suit are the same as those in an\neminent domain action.\u2019 \u201d ( Customer Co. v. City of Sacramento (1995) 10\nCal.4th 368, 377, fn. 4 [41 Cal.Rptr.2d 658, 895 P .2d 900], internal citations\nomitted.)\n\u2022 \u201cThe principle sought to be achieved by this concept \u2018is to reimburse the owner\nfor the property interest taken and to place the owner in as good a position\npecuniarily as if the property had not been taken.\u2019 \u201d ( Redevelopment Agency of\nthe City of Long Beach v. First Christian Church of Long Beach (1983) 140\nCal.App.3d 690, 705 [189 Cal.Rptr. 749], internal citation omitted, disapproved\n664\n\non other grounds in Los Angeles County Metropolitan Transportation Authority\nv. Continental Development Corp . (1997) 16 Cal.4th 694, 720\u2013721 [66\nCal.Rptr.2d 630, 941 P .2d 809].)\n\u2022 \u201cWe have long held that this jury right applies only to determining the\nappropriate amount of compensation, not to any other issues that arise in the\ncourse of condemnation proceedings.\u201d ( City of Perris, supra, 1 Cal.5th at p.\n593.)\n\u2022 \u201cAlthough the measure of compensation that is \u2018just\u2019 for purposes of both the\nfederal and state takings clause is often determined by the \u2018fair market value\u2019 of\nwhat has been lost, both federal and state takings cases uniformly recognize that\nthe fair market value standard is not applicable in all circumstances and that\nthere is no rigid or \ufb01xed standard that is appropriate in all settings.\u201d ( Property\nReserve, Inc. v. Superior Court (2016) 1 Cal.5th 151, 203\u2212204 [204 Cal.Rptr.3d\n770, 375 P .3d 887].)"
}